polars_features-0.1.7.dist-info/METADATA
polars_features-0.1.7.dist-info/WHEEL
polars_features-0.1.7.dist-info/licenses/LICENSE
functime/backtesting.py
functime/metrics/multi_objective.py
functime/metrics/__init__.py
functime/metrics/point.py
functime/metrics/probabilistic.py
functime/llm/__init__.py
functime/llm/formatting.py
functime/llm/api.py
functime/llm/common.py
functime/conformal.py
functime/seasonality/__init__.py
functime/seasonality/calendar.py
functime/seasonality/fourier.py
functime/type_aliases.py
functime/plotting.py
functime/evaluation.py
functime/conversion.py
functime/__init__.py
functime/_plotting.py
functime/ranges.py
functime/preprocessing.py
functime/_compat.py
functime/feature_extractors.py
functime/forecasting/snaive.py
functime/forecasting/elite.py
functime/forecasting/lightgbm.py
functime/forecasting/lance.py
functime/forecasting/linear.py
functime/forecasting/catboost.py
functime/forecasting/__init__.py
functime/forecasting/_reduction.py
functime/forecasting/naive.py
functime/forecasting/censored.py
functime/forecasting/xgboost.py
functime/forecasting/automl.py
functime/forecasting/_ar.py
functime/forecasting/_regressors.py
functime/forecasting/knn.py
functime/forecasting/_evaluate.py
functime/offsets.py
functime/base/__init__.py
functime/base/model.py
functime/base/metric.py
functime/base/transformer.py
functime/base/forecaster.py
functime/_utils.py
functime/cross_validation.py
functime/_functime_rust.abi3.so
polars_features-0.1.7.dist-info/RECORD
