Metadata-Version: 2.4
Name: polars-features
Version: 0.1.7
Classifier: Development Status :: 4 - Beta
Classifier: Intended Audience :: Developers
Classifier: Intended Audience :: Science/Research
Classifier: Programming Language :: Python :: 3 :: Only
Classifier: Programming Language :: Python :: 3.8
Classifier: Programming Language :: Python :: 3.9
Classifier: Programming Language :: Python :: 3.10
Classifier: Programming Language :: Python :: 3.11
Classifier: Programming Language :: Python :: 3.12
Classifier: Topic :: Scientific/Engineering
Classifier: Topic :: Software Development :: Libraries :: Python Modules
Requires-Dist: cloudpickle
Requires-Dist: flaml>=2.0.2
Requires-Dist: holidays
Requires-Dist: numpy
Requires-Dist: polars>=0.20.8
Requires-Dist: scikit-learn>=1.2.2
Requires-Dist: scipy==1.14.1
Requires-Dist: tqdm
Requires-Dist: kaleido==0.2.1 ; extra == 'plot'
Requires-Dist: pandas ; extra == 'plot'
Requires-Dist: plotly ; extra == 'plot'
Requires-Dist: catboost ; extra == 'cat'
Requires-Dist: lightgbm ; extra == 'lgb'
Requires-Dist: pyarrow ; extra == 'xgb'
Requires-Dist: xgboost ; extra == 'xgb'
Requires-Dist: pyarrow ; extra == 'ann'
Requires-Dist: pylance ; extra == 'ann'
Requires-Dist: catboost ; extra == 'tree'
Requires-Dist: lightgbm ; extra == 'tree'
Requires-Dist: pyarrow ; extra == 'tree'
Requires-Dist: xgboost ; extra == 'tree'
Requires-Dist: openai ; extra == 'llm'
Requires-Dist: pandas ; extra == 'llm'
Requires-Dist: tenacity ; extra == 'llm'
Requires-Dist: tiktoken ; extra == 'llm'
Requires-Dist: pyarrow ; extra == 'all'
Requires-Dist: pylance ; extra == 'all'
Requires-Dist: catboost ; extra == 'all'
Requires-Dist: lightgbm ; extra == 'all'
Requires-Dist: xgboost ; extra == 'all'
Requires-Dist: kaleido==0.2.1 ; extra == 'all'
Requires-Dist: pandas ; extra == 'all'
Requires-Dist: plotly ; extra == 'all'
Requires-Dist: pre-commit ; extra == 'dev'
Requires-Dist: jupyterlab ; extra == 'dev'
Requires-Dist: mkdocs ; extra == 'dev'
Requires-Dist: mkdocs-jupyter ; extra == 'dev'
Requires-Dist: mkdocs-material ; extra == 'dev'
Requires-Dist: mkdocstrings-python ; extra == 'dev'
Requires-Dist: pytest-cov>=5.0.0 ; extra == 'dev'
Requires-Dist: pytest-benchmark ; extra == 'dev'
Requires-Dist: pyarrow ; extra == 'dev'
Requires-Dist: pylance ; extra == 'dev'
Requires-Dist: catboost ; extra == 'dev'
Requires-Dist: lightgbm ; extra == 'dev'
Requires-Dist: xgboost ; extra == 'dev'
Requires-Dist: kaleido==0.2.1 ; extra == 'dev'
Requires-Dist: pandas ; extra == 'dev'
Requires-Dist: plotly ; extra == 'dev'
Requires-Dist: jupyterlab ; extra == 'doc'
Requires-Dist: mkdocs ; extra == 'doc'
Requires-Dist: mkdocs-jupyter ; extra == 'doc'
Requires-Dist: mkdocs-material ; extra == 'doc'
Requires-Dist: mkdocstrings-python ; extra == 'doc'
Requires-Dist: pytest-cov>=5.0.0 ; extra == 'test'
Requires-Dist: pytest-benchmark ; extra == 'test'
Requires-Dist: pyarrow ; extra == 'test'
Requires-Dist: pylance ; extra == 'test'
Requires-Dist: catboost ; extra == 'test'
Requires-Dist: lightgbm ; extra == 'test'
Requires-Dist: xgboost ; extra == 'test'
Requires-Dist: kaleido==0.2.1 ; extra == 'test'
Requires-Dist: pandas ; extra == 'test'
Requires-Dist: plotly ; extra == 'test'
Requires-Dist: aeon<0.5.0 ; extra == 'benchmark'
Requires-Dist: joblib ; extra == 'benchmark'
Requires-Dist: mlforecast==0.8.1 ; extra == 'benchmark'
Requires-Dist: pandas ; extra == 'benchmark'
Requires-Dist: pyarrow ; extra == 'benchmark'
Requires-Dist: pytest ; extra == 'benchmark'
Requires-Dist: pytest-memray ; extra == 'benchmark'
Requires-Dist: pytest-timeout ; extra == 'benchmark'
Requires-Dist: statsmodels ; extra == 'benchmark'
Requires-Dist: tsfresh ; extra == 'benchmark'
Requires-Dist: pytest-cov>=5.0.0 ; extra == 'benchmark'
Requires-Dist: pytest-benchmark ; extra == 'benchmark'
Requires-Dist: pyarrow ; extra == 'benchmark'
Requires-Dist: pylance ; extra == 'benchmark'
Requires-Dist: catboost ; extra == 'benchmark'
Requires-Dist: lightgbm ; extra == 'benchmark'
Requires-Dist: xgboost ; extra == 'benchmark'
Requires-Dist: kaleido==0.2.1 ; extra == 'benchmark'
Requires-Dist: pandas ; extra == 'benchmark'
Requires-Dist: plotly ; extra == 'benchmark'
Provides-Extra: plot
Provides-Extra: cat
Provides-Extra: lgb
Provides-Extra: xgb
Provides-Extra: ann
Provides-Extra: tree
Provides-Extra: llm
Provides-Extra: all
Provides-Extra: dev
Provides-Extra: doc
Provides-Extra: test
Provides-Extra: benchmark
License-File: LICENSE
Summary: Time-series machine learning at scale.
Author-email: Derek Snow <d.snow@sov.ai>
Maintainer-email: Derek Snow <d.snow@sov.ai>
Requires-Python: >=3.10
